kocrawl/__init__.py
kocrawl/base.py
kocrawl/config.py
kocrawl/daum_dict.py
kocrawl/daum_news.py
kocrawl/decorators.py
kocrawl/dust.py
kocrawl/map.py
kocrawl/restaurant.py
kocrawl/spell.py
kocrawl/weather.py
kocrawl/answerer/__init__.py
kocrawl/answerer/base_answerer.py
kocrawl/answerer/dust_answerer.py
kocrawl/answerer/map_answerer.py
kocrawl/answerer/restaurant_answerer.py
kocrawl/answerer/weather_answerer.py
kocrawl/editor/__init__.py
kocrawl/editor/base_editor.py
kocrawl/editor/dust_editor.py
kocrawl/editor/map_editor.py
kocrawl/editor/restaurant_editor.py
kocrawl/editor/weather_editor.py
kocrawl/searcher/__init__.py
kocrawl/searcher/base_searcher.py
kocrawl/searcher/daum_dict_searcher.py
kocrawl/searcher/daum_news_searcher.py
kocrawl/searcher/dust_searcher.py
kocrawl/searcher/map_searcher.py
kocrawl/searcher/restaurant_searcher.py
kocrawl/searcher/weather_searcher.py
tests/__init__.py
tests/test_daum_dict.py
tests/test_daum_news.py
tests/test_dust.py
tests/test_map.py
tests/test_spell.py
tests/test_weatherl.py
kocrawl-1.0.9.dist-info/LICENSE
kocrawl-1.0.9.dist-info/METADATA
kocrawl-1.0.9.dist-info/WHEEL
kocrawl-1.0.9.dist-info/top_level.txt
kocrawl-1.0.9.dist-info/RECORD
